mw_api_client/__init__.py
mw_api_client/excs.py
mw_api_client/misc.py
mw_api_client/page.py
mw_api_client/qyoo.py
mw_api_client/wiki.py
mw_api_client-3.2.2.dist-info/LICENSE
mw_api_client-3.2.2.dist-info/METADATA
mw_api_client-3.2.2.dist-info/WHEEL
mw_api_client-3.2.2.dist-info/top_level.txt
mw_api_client-3.2.2.dist-info/RECORD
