Metadata-Version: 2.1
Name: mw-api-client
Version: 3.2.2
Summary: A simple MediaWiki client.
Home-page: https://github.com/Kenny2github/mw-api-client
Author: Ken Hilton
License: MIT
Keywords: mediawiki api requests
Classifier: Development Status :: 4 - Beta
Classifier: Intended Audience :: Developers
Classifier: Topic :: Internet :: WWW/HTTP :: Dynamic Content :: Wiki
Classifier: License :: OSI Approved :: MIT License
Classifier: Programming Language :: Python :: 2.7
Classifier: Programming Language :: Python :: 3.6
Requires-Python: >=2.7
License-File: LICENSE
Requires-Dist: requests
Requires-Dist: six
